src/__init__.py
src/cli.py
src/sound_effects/error.wav
src/sound_effects/success.wav
ti_ding-1.3.0.dist-info/LICENSE
ti_ding-1.3.0.dist-info/METADATA
ti_ding-1.3.0.dist-info/WHEEL
ti_ding-1.3.0.dist-info/entry_points.txt
ti_ding-1.3.0.dist-info/top_level.txt
ti_ding-1.3.0.dist-info/RECORD
