Metadata-Version: 2.1
Name: ti-ding
Version: 1.3.0
Summary: A CLI tool to notify you with sound when a terminal process completes.
Author: Anand Chourasia
Author-email: anandchourasia007@gmail.com
License: MIT
Requires-Python: >=3.7
License-File: LICENSE
Requires-Dist: playsound==1.2.2
Requires-Dist: plyer
